hac/__init__.py
hac/commands.py
hac/core.py
hac/data.py
hac/parse_cli.py
hac/parse_common.py
hac/parse_config.py
hac/util_common.py
hac/util_data.py
hac/config/hacrc
hac/config/lang/temp.5.c
hac/config/lang/temp.5.cpp
hac/config/lang/temp.5.java
hac/config/lang/temp.5.pas
hac/config/lang/temp.5.py
hac/config/runner/c.clean.5.sh
hac/config/runner/c.dbg_compile.5.sh
hac/config/runner/c.dbg_run.5.sh
hac/config/runner/c.exec_compile.5.sh
hac/config/runner/c.exec_run.5.sh
hac/config/runner/c.variables.5.sh
hac/config/runner/cpp.clean.5.sh
hac/config/runner/cpp.dbg_compile.5.sh
hac/config/runner/cpp.dbg_run.5.sh
hac/config/runner/cpp.exec_compile.5.sh
hac/config/runner/cpp.exec_run.5.sh
hac/config/runner/cpp.variables.5.sh
hac/config/runner/java.clean.5.sh
hac/config/runner/java.dbg_compile.5.sh
hac/config/runner/java.dbg_run.5.sh
hac/config/runner/java.exec_compile.5.sh
hac/config/runner/java.exec_run.5.sh
hac/config/runner/java.variables.5.sh
hac/config/runner/pas.clean.5.sh
hac/config/runner/pas.dbg_compile.5.sh
hac/config/runner/pas.dbg_run.5.sh
hac/config/runner/pas.exec_compile.5.sh
hac/config/runner/pas.exec_run.5.sh
hac/config/runner/pas.variables.5.sh
hac/config/runner/py.clean.5.sh
hac/config/runner/py.dbg_compile.5.sh
hac/config/runner/py.dbg_run.5.sh
hac/config/runner/py.exec_compile.5.sh
hac/config/runner/py.exec_run.5.sh
hac/config/runner/py.variables.5.sh
hac/config/runner/temp.5.sh
hac/config/site/codechef.py
hac/config/site/codeforces.py
hac/config/site/local.py
hac/config/site/rosalind.py
hac/config/site/spoj.py
hac-1.0.5.dist-info/DESCRIPTION.rst
hac-1.0.5.dist-info/METADATA
hac-1.0.5.dist-info/RECORD
hac-1.0.5.dist-info/WHEEL
hac-1.0.5.dist-info/entry_points.txt
hac-1.0.5.dist-info/metadata.json
hac-1.0.5.dist-info/top_level.txt
