Metadata-Version: 2.0
Name: hac
Version: 1.0.5
Summary: hac - Helper for Algorithm Competitions
Home-page: https://github.com/plesiv/hac/blob/master/README.rst
Author: Zoran Plesivčak
Author-email: z@plesiv.com
License: hac.__license__
Download-URL: https://github.com/plesiv/hac
Keywords: algorithm competitions
Platform: UNKNOWN
Classifier: Development Status :: 3 - Alpha
Classifier: Environment :: Console
Classifier: Programming Language :: Python :: 2
Classifier: Programming Language :: Python :: 2.7
Classifier: Programming Language :: Python :: 3
Classifier: Programming Language :: Python :: 3.2
Classifier: Programming Language :: Python :: 3.3
Classifier: Programming Language :: Python :: 3.4
Classifier: Programming Language :: Python :: 3.5
Classifier: Intended Audience :: Education
Classifier: License :: OSI Approved :: GNU General Public License v2 (GPLv2)
Classifier: Topic :: Education
Requires-Dist: lxml (>=3.3.5)
Requires-Dist: requests (>=2.3.0)
